{
  "evolver": {
    "g1_center_ratio": 0.1314,
    "g1_avg_combo_per_place": 1.7373,
    "g1_placements_per_game": 28.79,
    "g2_combat_win_rate": 0.4671,
    "g2_avg_kills_per_game": 156.298,
    "g2_avg_damage_per_game": 160.516,
    "g2_draw_rate": 0.0903,
    "g3_avg_gold_earned": 160.118,
    "g3_avg_gold_spent": 105.801,
    "g3_gold_efficiency": 0.6608,
    "g3_avg_cards_per_game": 28.782,
    "g4_passive_triggers_per_game": 5.6,
    "g4_passive_delta_per_game": 5.933,
    "g5_win_rate": 0.111,
    "g5_avg_win_turn": 32.8559,
    "g5_avg_final_hp": 5.311,
    "g6_avg_power_per_card": 40.5608,
    "g6_r4r5_ratio": 0.235
  },
  "rare_hunter": {
    "g1_center_ratio": 0.2344,
    "g1_avg_combo_per_place": 1.8256,
    "g1_placements_per_game": 29.26,
    "g2_combat_win_rate": 0.498,
    "g2_avg_kills_per_game": 156.73,
    "g2_avg_damage_per_game": 180.091,
    "g2_draw_rate": 0.0876,
    "g3_avg_gold_earned": 148.055,
    "g3_avg_gold_spent": 115.401,
    "g3_gold_efficiency": 0.7794,
    "g3_avg_cards_per_game": 27.913,
    "g4_passive_triggers_per_game": 7.685,
    "g4_passive_delta_per_game": 7.754,
    "g5_win_rate": 0.186,
    "g5_avg_win_turn": 32.4247,
    "g5_avg_final_hp": 10.228,
    "g6_avg_power_per_card": 41.5809,
    "g6_r4r5_ratio": 0.2468
  },
  "random": {
    "g1_center_ratio": 0.1971,
    "g1_avg_combo_per_place": 1.3268,
    "g1_placements_per_game": 28.01,
    "g2_combat_win_rate": 0.3771,
    "g2_avg_kills_per_game": 52.826,
    "g2_avg_damage_per_game": 106.466,
    "g2_draw_rate": 0.1018,
    "g3_avg_gold_earned": 189.116,
    "g3_avg_gold_spent": 80.072,
    "g3_gold_efficiency": 0.4234,
    "g3_avg_cards_per_game": 27.636,
    "g4_passive_triggers_per_game": 3.603,
    "g4_passive_delta_per_game": 1.934,
    "g5_win_rate": 0.028,
    "g5_avg_win_turn": 34.5714,
    "g5_avg_final_hp": 0.915,
    "g6_avg_power_per_card": 36.6865,
    "g6_r4r5_ratio": 0.1932
  },
  "builder": {
    "g1_center_ratio": 0.1642,
    "g1_avg_combo_per_place": 2.0725,
    "g1_placements_per_game": 24.12,
    "g2_combat_win_rate": 0.3351,
    "g2_avg_kills_per_game": 60.417,
    "g2_avg_damage_per_game": 76.65,
    "g2_draw_rate": 0.1025,
    "g3_avg_gold_earned": 178.705,
    "g3_avg_gold_spent": 56.041,
    "g3_gold_efficiency": 0.3136,
    "g3_avg_cards_per_game": 21.65,
    "g4_passive_triggers_per_game": 5.393,
    "g4_passive_delta_per_game": 4.417,
    "g5_win_rate": 0.01,
    "g5_avg_win_turn": 33.7,
    "g5_avg_final_hp": 0.12,
    "g6_avg_power_per_card": 34.0821,
    "g6_r4r5_ratio": 0.1698
  },
  "economist": {
    "g1_center_ratio": 0.1303,
    "g1_avg_combo_per_place": 1.651,
    "g1_placements_per_game": 29.66,
    "g2_combat_win_rate": 0.4536,
    "g2_avg_kills_per_game": 159.835,
    "g2_avg_damage_per_game": 181.777,
    "g2_draw_rate": 0.0884,
    "g3_avg_gold_earned": 324.752,
    "g3_avg_gold_spent": 114.021,
    "g3_gold_efficiency": 0.3511,
    "g3_avg_cards_per_game": 26.642,
    "g4_passive_triggers_per_game": 6.073,
    "g4_passive_delta_per_game": 6.404,
    "g5_win_rate": 0.178,
    "g5_avg_win_turn": 33.1742,
    "g5_avg_final_hp": 6.205,
    "g6_avg_power_per_card": 40.8233,
    "g6_r4r5_ratio": 0.2539
  },
  "balancer": {
    "g1_center_ratio": 0.138,
    "g1_avg_combo_per_place": 1.6394,
    "g1_placements_per_game": 28.93,
    "g2_combat_win_rate": 0.4769,
    "g2_avg_kills_per_game": 158.396,
    "g2_avg_damage_per_game": 165.68,
    "g2_draw_rate": 0.0924,
    "g3_avg_gold_earned": 153.532,
    "g3_avg_gold_spent": 115.221,
    "g3_gold_efficiency": 0.7505,
    "g3_avg_cards_per_game": 28.811,
    "g4_passive_triggers_per_game": 8.065,
    "g4_passive_delta_per_game": 8.764,
    "g5_win_rate": 0.143,
    "g5_avg_win_turn": 32.4825,
    "g5_avg_final_hp": 7.74,
    "g6_avg_power_per_card": 41.707,
    "g6_r4r5_ratio": 0.2428
  },
  "warrior": {
    "g1_center_ratio": 0.2355,
    "g1_avg_combo_per_place": 1.8379,
    "g1_placements_per_game": 29.34,
    "g2_combat_win_rate": 0.5013,
    "g2_avg_kills_per_game": 158.509,
    "g2_avg_damage_per_game": 181.693,
    "g2_draw_rate": 0.0896,
    "g3_avg_gold_earned": 151.864,
    "g3_avg_gold_spent": 117.531,
    "g3_gold_efficiency": 0.7739,
    "g3_avg_cards_per_game": 29.271,
    "g4_passive_triggers_per_game": 8.314,
    "g4_passive_delta_per_game": 8.521,
    "g5_win_rate": 0.179,
    "g5_avg_win_turn": 32.2123,
    "g5_avg_final_hp": 11.386,
    "g6_avg_power_per_card": 41.8235,
    "g6_r4r5_ratio": 0.2448
  },
  "tempo": {
    "g1_center_ratio": 0.1908,
    "g1_avg_combo_per_place": 1.792,
    "g1_placements_per_game": 29.13,
    "g2_combat_win_rate": 0.4975,
    "g2_avg_kills_per_game": 162.046,
    "g2_avg_damage_per_game": 179.078,
    "g2_draw_rate": 0.0902,
    "g3_avg_gold_earned": 148.871,
    "g3_avg_gold_spent": 116.26,
    "g3_gold_efficiency": 0.7809,
    "g3_avg_cards_per_game": 29.054,
    "g4_passive_triggers_per_game": 7.838,
    "g4_passive_delta_per_game": 8.272,
    "g5_win_rate": 0.165,
    "g5_avg_win_turn": 31.897,
    "g5_avg_final_hp": 10.119,
    "g6_avg_power_per_card": 41.7909,
    "g6_r4r5_ratio": 0.2436
  }
}